{"HsQ5EsyiSN1JoNS1wxKTlA==":"mbr.jpg","vb0NXXMWYVftnmm9UkZhEg==":"mbr-1.jpg","RrQaCwc6IdplCRKHaQKp7A==":"mbr-2.jpg","q/X8EJRANHufD8muSzIinA==":"mbr-3.jpg","aZ16PG29McALiafJwU5Jhw==":"mbr-4.jpg","rzbUtRGffeFAbKPJLnk4ww==":"mbr-4.jpeg","J5jO+opoXAVNvVA9jP+W6g==":"mbr-3.jpeg","Ha2u2BZCY4gE4tLBG8kGhg==":"mbr-5.jpg","jrBPsm93wISe7uFwE9rLGg==":"mbr-6.jpg","05/MKuM/LzY8qQdBEbthKA==":"mbr-7.jpg","TlPEJUw7Ra7ShfGEgotOOA==":"mbr-8.jpg","AUJNsUcygc2AexLup8NmEA==":"mbr-9.jpg","a2VLKiVcqrWbbbcW0n70sA==":"mbr-9.jpeg","PHP06/puSNfIcwT/dKHBLw==":"mbr-1920x1783.jpg","SFvb0Jy/q0wyoFzb6NOp0A==":"nature_logo-225x225.png","WRqbEkogjNmcMRHN41m6Cg==":"logo-nature-physics-3-e1592470819230-240x240.png","7Ve6NwJgxSxr84PiPQ9h2Q==":"new_full_logo-black-2500w-240x24.png","/rTXFhld4cHnnXl2e0EDjA==":"mbr-1920x1783.jpeg","LBInkt9Efh55iiA0lQW1dQ==":"car-2-1900x1267.jpg","UAADiityY/tHJaHItfutBA==":"car-1-626x488.png","a6DRdIGT2itz6EcZhUX6jg==":"mbr-282x169.jpg","3PCaqVbH8oW+ySdDODYdyg==":"mbr-282x212.jpg","GqPVp4og1eEK/nt6sLs4lg==":"mbr-282x188.jpg","390A+3SovsOr6ByugFhR6A==":"mbr-1-282x188.jpg","w8vagwArKgCZVHFZ9FpN1g==":"mbr-1-282x188.jpeg","GpNZm52EG/ncsqtzvlX6Fw==":"mbr-5.jpeg","B5RmtaECtZlbHLUv85pYCQ==":"mbr-282x188.jpeg","VE1PLzOm4+adGIb37QrcWQ==":"mbr-2-282x188.jpeg"}